unstable/.__init__.py.swp
unstable/.__init__.py.un~
unstable/__init__.py
unstable-0.5.1.dist-info/WHEEL
unstable-0.5.1.dist-info/METADATA
unstable-0.5.1.dist-info/RECORD
