Metadata-Version: 1.2
Name: unstable
Version: 0.5.1
Summary: Unstable
Home-page: https://github.com/Carreau/unstable
License: UNKNOWN
Author: Matthias Bussonnier
Author-email: bussonniermatthias@gmail.com
Requires-Python: >=3
Classifier: License :: OSI Approved :: BSD License
